LICENSE
MANIFEST.in
README.md
setup.py
translate/__init__.py
translate/__main__.py
translate/translate.py
translate_term.egg-info/PKG-INFO
translate_term.egg-info/SOURCES.txt
translate_term.egg-info/dependency_links.txt
translate_term.egg-info/entry_points.txt
translate_term.egg-info/requires.txt
translate_term.egg-info/top_level.txt