Metadata-Version: 1.0
Name: translate-term
Version: 0.1.3
Summary: Command line translator pulling from wordreference.com and coded in Python
Home-page: https://github.com/kevinolivier/translate-term
Author: Kevin Olivier
Author-email: kevin.olivier@outlook.com
License: MIT
Keywords: shell bash zsh terminal translate wordreference
Platform: UNKNOWN
